src/pipeline/instruction_fetch.v
module InstructionFetch(input wire clk,
                        input wire cs,
                        input wire [31:0] read_memory,
                        input wire [15:0] read_data_reg,
                        output reg rd,
                        output reg wn,
                        output reg [15:0] address,
                        output reg [3:0] reg_id,
                        output reg rdi,
                        output reg wni,
                        output reg [15:0] write_data_reg,
                        output reg [31:0] instruction);
    
    
    
    
    
    always @ (posedge clk)
    begin
        if (cs == 1'b1) begin
            wni    = 1'b0;
            rdi    = 1'b1;
            reg_id = 4'b0000;
            
            address = read_data_reg;
            
            wn = 1'b0;
            rd = 1'b1;
            
            instruction = read_memory;
            
            wni = 1'b1;
            rdi = 1'b0;
            
            write_data_reg = read_data_reg + 1;
        end
        
    end
    
endmodule

src/register/register.v
module Register(input clk,
                input reset,
                input rd,
                input wn,
                input wire [3:0] reg_id,
                input wire [15:0] write_data,
                output reg [15:0] read_data);
    
    reg [15:0] register_memory[16:0];
    
    integer count;
    
    always @ (posedge clk or reset) begin
        if (reset == 1'b1) begin
            for (count = 0;count<16 ; count++) begin
                register_memory[count] = 16'h0;
            end
        end
        else begin
            if (rd == 1'b1 && wn == 1'b0) read_data      = register_memory[reg_id];
            else if (rd == 1'b0 && wn == 1'b1) register_memory[reg_id] = write_data;
        end
    end
    
endmodule

src/memory/instruction_memory.v
module InstructionMemory(input clk,
              input rd,
              input wn,
              input [15:0] address,
              input [31:0] write_data,
              output wire [31:0] read_data);
    
    reg [31:0] sRAM[2047:0];
    assign read_data   = sRAM[address];
    initial begin
        sRAM[0] = 1;
        sRAM[1] = 2;
        sRAM[2] = 3;
        sRAM[3] = 4;
        sRAM[4] = 5;
        sRAM[5] = 6;
        sRAM[6] = 7;
        sRAM[7] = 8;
    end
    
    always @ (posedge clk) begin
        if (rd == 1'b0 && wn == 1'b1) sRAM[address] <= write_data;
    end
    
    
endmodule

testbench/instruction_fetch_tb.v
`timescale 1ns/1ns

module instruction_fetch_tb;

    // Inputs
    reg [31:0] dataIn;
    reg [15:0] address;
    reg wn;
    reg rd;
    reg clk;
    reg reset;
    reg cs;
    
    // Outputs
    
    wire [31:0] dataOut;
    
    reg rdi;
    reg wni;
    reg [3:0] reg_id;
    reg [15:0] write_data_reg;
    wire [15:0] read_data_reg;
    
    
    wire [31:0] instruction;
    
    wire i_rd;
    wire i_wn;
    wire [15:0] i_address;
    wire [3:0] i_reg_id;
    wire i_rdi;
    wire i_wni;
    wire [15:0] i_write_data_reg;
    wire [31:0] i_instruction;
    
    assign i_rd = rd;
    assign i_wn = wn;
    
    InstructionMemory memory (
    .write_data(dataIn),
    .read_data(dataOut),
    .address(address),
    .wn(wn),
    .rd(rd),
    .clk(clk)
    );
    
    Register register(.clk(clk),
    .reset(reset),
    .rd(rdi),
    .wn(wni),
    .reg_id(reg_id),
    .write_data(write_data_reg),
    .read_data(read_data_reg));
    
    InstructionFetch instruction_fetch(.clk(clk),
    .cs(cs),
    .read_memory(dataOut),
    .read_data_reg(read_data_reg),
    .rd(i_rd),
    .wn(i_wn),
    .address(i_address),
    .reg_id(i_reg_id),
    .rdi(i_rdi),
    .wni(i_wni),
    .write_data_reg(i_write_data_reg),
    .instruction(instruction));

    assign i_address        = address;
    assign i_reg_id         = reg_id;
    assign i_rdi            = rdi;
    assign i_wni            = wni;
    assign i_write_data_reg = write_data_reg;


    initial begin
        $dumpfile("vcd/instruction_fetch_tb.vcd");

        $dumpvars(0,memory);
        $dumpvars(0,register);
        $dumpvars(0,instruction_fetch);

        // initialize input

                // Initialize Inputs
        dataIn  <= 32'h0;
        address  <= 16'h0;
        reset  <= 1'b0;
        wn  <= 1'b0;
        rd  <= 1'b0;
        clk  <= 1'b0;
        cs <= 1'b0;

        // Wait 100 ns for global reset to finish
        #100;
        
        // Add stimulus here

        dataIn  <= 32'h0;
        address  <= 16'h0;
        wn  <= 1'b1;
        rd  <= 1'b0;

        #20;

        dataIn  <= 32'h0;
        address  <= 16'h0;
        #20;

        dataIn  <= 32'h1;
        address  <= 16'h1;
        #20;

        dataIn  <= 32'h10;
        address  <= 16'h2;
        #20;

        dataIn  <= 32'h6;
        address  <= 16'h3;
        #20;
        reset = ~ reset;
        #30;
        reset = ~ reset;

        #5000;

        $finish;


    end
    
    always #10 clk=~clk;

endmodule

vcd/instruction_fetch_tb.vcd
$date
	Tue Jan 19 01:44:35 2021
$end
$version
	Icarus Verilog
$end
$timescale
	1ns
$end
$scope module instruction_fetch_tb $end
$scope module memory $end
$var wire 16 ! address [15:0] $end
$var wire 1 " clk $end
$var wire 1 # rd $end
$var wire 1 $ wn $end
$var wire 32 % write_data [31:0] $end
$var reg 32 & read_data [31:0] $end
$upscope $end
$upscope $end
$scope module instruction_fetch_tb $end
$scope module register $end
$var wire 1 " clk $end
$var wire 1 ' rd $end
$var wire 4 ( reg_id [3:0] $end
$var wire 1 ) reset $end
$var wire 1 * wn $end
$var wire 16 + write_data [15:0] $end
$var reg 16 , read_data [15:0] $end
$var integer 32 - count [31:0] $end
$upscope $end
$upscope $end
$scope module instruction_fetch_tb $end
$scope module instruction_fetch $end
$var wire 1 " clk $end
$var wire 1 . cs $end
$var wire 32 / read_memory [31:0] $end
$var wire 16 0 read_data_reg [15:0] $end
$var reg 16 1 address [15:0] $end
$var reg 32 2 instruction [31:0] $end
$var reg 1 3 rd $end
$var reg 1 4 rdi $end
$var reg 4 5 reg_id [3:0] $end
$var reg 1 6 wn $end
$var reg 1 7 wni $end
$var reg 16 8 write_data_reg [15:0] $end
$upscope $end
$upscope $end
$enddefinitions $end
#0
$dumpvars
bx 8
x7
x6
bx 5
x4
x3
bx 2
bx 1
bx 0
bx /
0.
bx -
bx ,
bx +
x*
0)
bx (
x'
bx &
b0 %
0$
0#
0"
b0 !
$end
#10
1"
#20
0"
#30
1"
#40
0"
#50
1"
#60
0"
#70
1"
#80
0"
#90
1"
#100
1$
0"
#110
1"
#120
0"
#130
1"
#140
b1 !
b1 %
0"
#150
1"
#160
b10 !
b10000 %
0"
#170
1"
#180
b11 !
b110 %
0"
#190
1"
#200
b10000 -
0"
1)
#210
b10000 -
1"
#220
0"
#230
1"
0)
