src/pipeline/instruction_decode.v
module InstructionDecode(input clk,
                         input wire [23:0] instruction,

                         input wire [15:0] reg_data1,
                         input wire [15:0] reg_data2,

                         input wire [15:0] mem_data,

                         output wire rd_en_reg1,
                         output wire wr_en_reg1,

                         output wire rd_en_reg2,
                         output wire wr_en_reg2,

                         output wire rd_en_mem,
                         output wire wr_en_mem,

                         output wire [3:0] reg_id1,
                         output wire [3:0] reg_id2,

                         output wire [15:0] mem_addr,
                         output wire [5:0] opcode,

                         output wire [1:0] mode,
                         output wire [15:0] op1,
                         output wire [15:0] op2);


    reg rd_en_reg1_temp;
    reg rd_en_reg2_temp;
    reg wr_en_reg1_temp;
    reg wr_en_reg2_temp;

    reg rd_en_mem_temp;
    reg wr_en_mem_temp;

    reg [3:0] reg_id1_temp;
    reg [3:0] reg_id2_temp;

    reg [15:0] mem_addr_temp;

    assign opcode = instruction[23:18];
    assign mode = instruction[17:16];

    assign rd_en_reg1 = rd_en_reg1_temp;
    assign rd_en_reg2 = rd_en_reg2_temp;
    assign wr_en_reg1 = wr_en_reg1_temp;
    assign wr_en_reg2 = wr_en_reg2_temp;

    assign reg_id1 = reg_id1_temp;
    assign reg_id2 = reg_id2_temp;

    assign rd_en_mem = rd_en_mem_temp;
    assign wr_en_mem = wr_en_mem_temp;

    assign mem_addr = mem_addr_temp;

    assign op1 = reg_data1;
    assign op2 = (mode == 2'b00)? reg_data2 : ((mode == 2'b01)? mem_data : ((mode == 2'b10)? {4'b0000, instruction[11:0]} : 16'b0));

    always @ (posedge clk) begin

      // op1 fetch
      rd_en_reg1_temp = 1'b1;
      wr_en_reg1_temp = 1'b0;
      reg_id1_temp = instruction[15:12];

      case(mode)

        2'b00: begin
          // op2 fetch
          rd_en_reg2_temp = 1'b1;
          wr_en_reg2_temp = 1'b0;
          reg_id2_temp = instruction[11:8];
        end

        2'b01: begin
          // op2 fetch
          rd_en_mem_temp = 1'b1;
          wr_en_mem_temp = 1'b0;
          mem_addr_temp = {4'b0000, instruction[11:0]};
        end
      endcase
    end
endmodule

src/register/register.v
module Register(input wire clk,
                input wire reset,
                input wire rd1,
                input wire wn1,
                input wire rd2,
                input wire wn2,
                input wire [3:0] reg_id1,
                input wire [3:0] reg_id2,
                input wire [15:0] write_data1,
                input wire [15:0] write_data2,
                output wire [15:0] read_data1,
                output wire [15:0] read_data2);

    reg [15:0] register_memory[15:0];

    assign read_data1 = (rd1 == 1'b1 && wn1 == 1'b0)? register_memory[reg_id1] : 16'h0;
    assign read_data2 = (rd2 == 1'b1 && wn2 == 1'b0)? register_memory[reg_id2] : 16'h0;

    integer i;

    initial begin
      for(i=0; i< 16; i++) begin
        register_memory[i] = i+5;
      end
    end

    always @ (posedge clk) begin
        if (rd1 == 1'b0 && wn1 == 1'b1)  begin
            register_memory[reg_id2] = write_data1;
        end

        if (rd2 == 1'b0 && wn2 == 1'b1)  begin
            register_memory[reg_id2] = write_data2;
        end
    end

endmodule

src/memory/data_memory.v
module DataMemory(input clk,
              input rd,
              input wn,
              input wire [15:0] address,
              input wire mode,
              input wire [15:0] write_data,
              output wire [15:0] read_data);

    reg [7:0] sRAM[2047:0];

    integer i;

    initial begin
      for(i=0; i< 16; i++) begin
        sRAM[i] = i+1;
      end
    end

    assign read_data = (rd == 1'b1 && wn == 1'b0) ? {sRAM[address], sRAM[address + 1]}: 16'b0;

    always @ (negedge clk) begin
        if (rd == 1'b0 && wn == 1'b1) begin
            if (mode == 1'b0) begin
                {sRAM[address], sRAM[address+1]} <= write_data;
            end
            else if (mode == 1'b1) begin
                sRAM[address] <= write_data[7:0];
            end
        end
    end

endmodule

testbench/instruction_decode_tb.v
`timescale 1ns/1ns

module instruction_fetch_tb;

    reg clk;
    reg reset;
    reg [23:0] instruction;
    wire rd_mem;
    wire wr_mem;
    wire rd_reg1;
    wire wn_reg1;
    wire rd_reg2;
    wire wn_reg2;
    wire mode_mem;
    wire [3:0] reg_id1;
    wire [3:0] reg_id2;
    wire [15:0] reg_data1;
    wire [15:0] reg_data2;
    wire [15:0] write_data1;
    wire [15:0] write_data2;
    wire [15:0] write_data_mem;
    wire [15:0] mem_data;
    wire [15:0] address;

    wire [5:0] opcode;
    wire [1:0] mode;
    wire [15:0] op1;
    wire [15:0] op2;

    assign  wn = 1'b0;
    assign  rd = 1'b1;

    DataMemory data_memory (clk, rd_mem, wr_mem, address, mode_mem, write_data_mem, mem_data);

    Register register(clk, reset, rd_reg1, wn_reg1, rd_reg2, wn_reg2, reg_id1, reg_id2, write_data1, write_data2, reg_data1, reg_data2);

    InstructionDecode instruction_decode(clk, instruction, reg_data1, reg_data2, mem_data, rd_reg1, wn_reg1, rd_reg2, wn_reg2, rd_mem, wr_mem, reg_id1, reg_id2, address, opcode, mode, op1, op2);

    // IF_ID_latch if_id_latch(clk, instruction, instruction_out);

    initial begin

        $dumpfile("vcd/instruction_decode_tb.vcd");
        $dumpvars(0, instruction_fetch_tb);

        // Initialize Inputs

        clk  <= 1'b0;

        // Wait 100 ns for global reset to finish
        #100;

        // Add stimulus here

        instruction <= 24'b000000_00_0110_00000000100;
        #20
        instruction <= 24'b000100_01_0011_000000000110;
        #20
        instruction <= 24'b000011_00_0110_00000000100;
        #20
        instruction <= 24'b000100_10_0011_000000000110;
        #20
        // instruction <= 24'b11000000011000000000100;
        // #20
        // instruction <= 24'b000110010011000000000110;
        #1000

        $finish;

    end

    always #10 clk=~clk;

endmodule

vcd/instruction_decode_tb.vcd
$date
	Sun Mar  7 19:32:20 2021
$end
$version
	Icarus Verilog
$end
$timescale
	1ns
$end
$scope module instruction_fetch_tb $end
$var wire 1 ! mode_mem $end
$var wire 1 " rd $end
$var wire 1 # wn $end
$var wire 16 $ write_data1 [15:0] $end
$var wire 16 % write_data2 [15:0] $end
$var wire 16 & write_data_mem [15:0] $end
$var wire 1 ' wr_mem $end
$var wire 1 ( wn_reg2 $end
$var wire 1 ) wn_reg1 $end
$var wire 4 * reg_id2 [3:0] $end
$var wire 4 + reg_id1 [3:0] $end
$var wire 16 , reg_data2 [15:0] $end
$var wire 16 - reg_data1 [15:0] $end
$var wire 1 . rd_reg2 $end
$var wire 1 / rd_reg1 $end
$var wire 1 0 rd_mem $end
$var wire 6 1 opcode [5:0] $end
$var wire 16 2 op2 [15:0] $end
$var wire 16 3 op1 [15:0] $end
$var wire 2 4 mode [1:0] $end
$var wire 16 5 mem_data [15:0] $end
$var wire 16 6 address [15:0] $end
$var reg 1 7 clk $end
$var reg 24 8 instruction [23:0] $end
$var reg 1 9 reset $end
$scope module data_memory $end
$var wire 1 7 clk $end
$var wire 1 ! mode $end
$var wire 16 : write_data [15:0] $end
$var wire 1 ' wn $end
$var wire 16 ; read_data [15:0] $end
$var wire 1 0 rd $end
$var wire 16 < address [15:0] $end
$var integer 32 = i [31:0] $end
$upscope $end
$scope module instruction_decode $end
$var wire 1 7 clk $end
$var wire 24 > instruction [23:0] $end
$var wire 16 ? mem_data [15:0] $end
$var wire 16 @ op1 [15:0] $end
$var wire 1 ( wr_en_reg2 $end
$var wire 1 ) wr_en_reg1 $end
$var wire 1 ' wr_en_mem $end
$var wire 4 A reg_id2 [3:0] $end
$var wire 4 B reg_id1 [3:0] $end
$var wire 16 C reg_data2 [15:0] $end
$var wire 16 D reg_data1 [15:0] $end
$var wire 1 . rd_en_reg2 $end
$var wire 1 / rd_en_reg1 $end
$var wire 1 0 rd_en_mem $end
$var wire 6 E opcode [5:0] $end
$var wire 16 F op2 [15:0] $end
$var wire 2 G mode [1:0] $end
$var wire 16 H mem_addr [15:0] $end
$var reg 16 I mem_addr_temp [15:0] $end
$var reg 1 0 rd_en_mem_temp $end
$var reg 1 / rd_en_reg1_temp $end
$var reg 1 . rd_en_reg2_temp $end
$var reg 4 J reg_id1_temp [3:0] $end
$var reg 4 K reg_id2_temp [3:0] $end
$var reg 1 ' wr_en_mem_temp $end
$var reg 1 ) wr_en_reg1_temp $end
$var reg 1 ( wr_en_reg2_temp $end
$upscope $end
$scope module register $end
$var wire 1 7 clk $end
$var wire 1 / rd1 $end
$var wire 1 . rd2 $end
$var wire 4 L reg_id1 [3:0] $end
$var wire 4 M reg_id2 [3:0] $end
$var wire 1 9 reset $end
$var wire 1 ) wn1 $end
$var wire 1 ( wn2 $end
$var wire 16 N write_data1 [15:0] $end
$var wire 16 O write_data2 [15:0] $end
$var wire 16 P read_data2 [15:0] $end
$var wire 16 Q read_data1 [15:0] $end
$var integer 32 R i [31:0] $end
$upscope $end
$upscope $end
$enddefinitions $end
#0
$dumpvars
b10000 R
bx Q
bx P
bz O
bz N
bx M
bx L
bx K
bx J
bx I
bx H
bx G
bx F
bx E
bx D
bx C
bx B
bx A
bx @
bx ?
bx >
b10000 =
bx <
bx ;
bz :
x9
bx 8
07
bx 6
bx 5
bx 4
bx 3
bx 2
bx 1
x0
x/
x.
bx -
bx ,
bx +
bx *
x)
x(
x'
bz &
bz %
bz $
0#
1"
z!
$end
#10
0)
1/
17
#20
07
#30
17
#40
07
#50
17
#60
07
#70
17
#80
07
#90
17
#100
b0 1
b0 E
b0 4
b0 G
b11000000000100 8
b11000000000100 >
07
#110
b101 2
b101 F
b101 ,
b101 C
b101 P
b1000 3
b1000 @
b1000 -
b1000 D
b1000 Q
b0 *
b0 A
b0 K
b0 M
0(
1.
b11 +
b11 B
b11 J
b11 L
17
#120
bx 2
bx F
b100 1
b100 E
b1 4
b1 G
b100010011000000000110 8
b100010011000000000110 >
07
#130
b11100001000 2
b11100001000 F
b11100001000 5
b11100001000 ;
b11100001000 ?
b110 6
b110 <
b110 H
b110 I
0'
10
17
#140
b100 2
b100 F
b1 1
b1 E
b10 4
b10 G
b1100011000000000100 8
b1100011000000000100 >
07
#150
17
#160
b110 2
b110 F
b100 1
b100 E
b100100011000000000110 8
b100100011000000000110 >
07
