src/register/register.v
module Register(input clk,
                input reset,
                input rd,
                input wn,
                input stack_en,
                input push_en,
                input pop_en,
                // input carry_flag_in,
                // input less_flag_in,
                // input 
                input wire [3:0] reg_id,
                input wire [15:0] write_data,
                output reg [15:0] read_data);
    
    reg [15:0] register_memory[15:0];
    
    
    always @ (posedge clk or reset) begin
        
        if (rd == 1'b1 && wn == 1'b0) begin
            read_data = register_memory[reg_id];
        end
        else if (rd == 1'b0 && wn == 1'b1)  begin
            register_memory[reg_id] = write_data;
        end
            
        if (stack_en == 1'b1 && push_en == 1'b1 && pop_en == 1'b0) begin
                register_memory[2] = register_memory[2] + 1;
        end
        else if (stack_en == 1'b1 && pop_en == 1'b1 && push_en == 1'b0) begin
                register_memory[2] = register_memory[2] - 1;
        end
    end              
endmodule

testbench/register_tb.v
`timescale 1ns / 1ns

module register_tb;
    reg clk;
    reg reset;
    reg rd;
    reg wn;
    reg stack_en;
    reg push_en;
    reg pop_en;
    reg [3:0] reg_id;
    reg [15:0] write_data;
    wire [15:0] read_data;

    Register UUT(clk,
                reset,
                rd,
                wn,
                stack_en,
                push_en,
                pop_en,
                reg_id,
                write_data,
                read_data);

initial begin
    $dumpfile("vcd/register.vcd");
    $dumpvars(0,UUT);
    clk        = 0;
    rd         = 0;
    wn         = 1;
    reg_id     = 2;
    write_data = 15;
    stack_en   = 0;
    #25
    stack_en = 1;
    pop_en   = 0;
    push_en  = 1;
    rd       = 1;
    wn       = 0;
    
    #35
    stack_en = 1;
    pop_en   = 1;
    push_en  = 0;
    
    #25
    stack_en = 0;
    rd       = 1;
    wn       = 0;
    #100
    $finish;
end

always #10 clk <= ~clk;
endmodule

vcd/register.vcd
$date
	Mon Feb 15 11:20:16 2021
$end
$version
	Icarus Verilog
$end
$timescale
	1ns
$end
$scope module register_tb $end
$scope module UUT $end
$var wire 1 ! clk $end
$var wire 1 " pop_en $end
$var wire 1 # push_en $end
$var wire 1 $ rd $end
$var wire 4 % reg_id [3:0] $end
$var wire 1 & reset $end
$var wire 1 ' stack_en $end
$var wire 1 ( wn $end
$var wire 16 ) write_data [15:0] $end
$var reg 16 * read_data [15:0] $end
$upscope $end
$upscope $end
$enddefinitions $end
#0
$dumpvars
bx *
b1111 )
1(
0'
x&
b10 %
0$
x#
x"
0!
$end
#10
1!
#20
0!
#25
0(
1$
1#
0"
1'
#30
b1111 *
1!
#40
0!
#50
b10000 *
1!
#60
0!
0#
1"
#70
b10001 *
1!
#80
0!
#85
0'
#90
b10000 *
1!
